magcode/__init__.py
magcode/core/__init__.py
magcode/core/globals_.py
magcode/core/logging.py
magcode/core/process.py
magcode/core/system_editor_pager.py
magcode/core/template_cache.py
magcode/core/utility.py
magcode/core/database/__init__.py
magcode/core/database/event.py
magcode/core/database/process_sm.py
magcode/core/database/state_machine.py
magcode/core/database/utility.py
magcode/core/wsgi/__init__.py
magcode/core/wsgi/jsonrpc_server.py
magcode_core-1.4.10.dist-info/DESCRIPTION.rst
magcode_core-1.4.10.dist-info/METADATA
magcode_core-1.4.10.dist-info/RECORD
magcode_core-1.4.10.dist-info/WHEEL
magcode_core-1.4.10.dist-info/metadata.json
magcode_core-1.4.10.dist-info/top_level.txt
