Metadata-Version: 2.0
Name: magcode-core
Version: 1.4.10
Summary: MAG Code Core utility module
Home-page: UNKNOWN
Author: Matthew Grant
Author-email: matt@mattgrant.net.nz
License: UNKNOWN
Platform: UNKNOWN
